ingot_h2/__init__.py
ingot_h2/bootstrap/__init__.py
ingot_h2/bootstrap/base.py
ingot_h2/bootstrap/scaffolding/__init__.py
ingot_h2/contrib/__init__.py
ingot_h2/scripts/__init__.py
ingot_h2/scripts/ingot_h2.py
ingot_h2/tests/__init__.py
ingot_h2/tests/functionals/__init__.py
ingot_h2/tests/units/__init__.py
ingot_h2/tests/units/bootstrap/__init__.py
ingot_h2/tests/units/bootstrap/test_base.py
ingot_h2/tests/units/contrib/__init__.py
ingot_h2/tests/units/scripts/__init__.py
ingot_h2/tests/units/scripts/test_ingot_h2.py
ingot_h2-0.1.0.dist-info/LICENSE
ingot_h2-0.1.0.dist-info/METADATA
ingot_h2-0.1.0.dist-info/WHEEL
ingot_h2-0.1.0.dist-info/entry_points.txt
ingot_h2-0.1.0.dist-info/top_level.txt
ingot_h2-0.1.0.dist-info/RECORD
